nakv.py
nadb/__init__.py
storage_backends/__init__.py
storage_backends/fs.py
storage_backends/memcache.py
storage_backends/redis.py
nadb-0.1.6.dist-info/METADATA
nadb-0.1.6.dist-info/WHEEL
nadb-0.1.6.dist-info/top_level.txt
nadb-0.1.6.dist-info/RECORD
