Metadata-Version: 2.4
Name: nadb
Version: 0.1.6
Summary: A simple, thread-safe, zero external dependencies key-value store with asynchronous memory buffering capabilities, binary data support, tagging system, data compression, and pluggable storage backends.
Home-page: https://github.com/lsferreira42/nadb
Author: Leandro Ferreira
Author-email: leandrodsferreira@gmail.com
Keywords: database,key-value,nosql,storage,memory,disk,persistence,tagging,redis
Classifier: Development Status :: 4 - Beta
Classifier: Intended Audience :: Developers
Classifier: License :: OSI Approved :: MIT License
Classifier: Programming Language :: Python :: 3
Classifier: Programming Language :: Python :: 3.7
Classifier: Programming Language :: Python :: 3.8
Classifier: Programming Language :: Python :: 3.9
Classifier: Programming Language :: Python :: 3.10
Classifier: Programming Language :: Python :: 3.11
Classifier: Topic :: Database
Classifier: Topic :: Software Development :: Libraries
Classifier: Topic :: Software Development :: Libraries :: Python Modules
Requires-Python: >=3.7
Provides-Extra: redis
Requires-Dist: redis>=3.5.0; extra == "redis"
Provides-Extra: dev
Requires-Dist: pytest>=6.0.0; extra == "dev"
Requires-Dist: pytest-cov>=2.10.0; extra == "dev"
Dynamic: author
Dynamic: author-email
Dynamic: classifier
Dynamic: description
Dynamic: description-content-type
Dynamic: home-page
Dynamic: keywords
Dynamic: provides-extra
Dynamic: requires-python
Dynamic: summary
